eldar_text_art/__init__.py
eldar_text_art/ascii_art.py
eldar_text_art/banner.py
eldar_text_art/emoji_art.py
eldar_text_art/fun_effects.py
eldar_text_art/shapes.py
eldar_text_art/test.py
eldar_text_art/text_effects.py
eldar_text_art-1.2.0.dist-info/METADATA
eldar_text_art-1.2.0.dist-info/WHEEL
eldar_text_art-1.2.0.dist-info/top_level.txt
eldar_text_art-1.2.0.dist-info/RECORD
