Metadata-Version: 2.4
Name: eldar_text_art
Version: 1.2.0
Summary: Advanced text and emoji art library with fun effects (by Eldar)
Author: Eldar Eliyev
Author-email: example@email.com
Requires-Python: >=3.8
Dynamic: author
Dynamic: author-email
Dynamic: requires-python
Dynamic: summary
